air_migrations/__init__.py
air_migrations/cli.py
air_migrations/utils.py
air_migrations-1.0.1.dist-info/METADATA
air_migrations-1.0.1.dist-info/WHEEL
air_migrations-1.0.1.dist-info/entry_points.txt
air_migrations-1.0.1.dist-info/top_level.txt
air_migrations-1.0.1.dist-info/RECORD
