Metadata-Version: 2.1
Name: air-migrations
Version: 1.0.1
Summary: Portable migrations
Author: MSNLP
Requires-Python: >=3.11.0
Requires-Dist: alembic <2.0.0,>=1.13.2
Requires-Dist: sqlalchemy <3.0.0,>=2.0.31
Requires-Dist: asyncpg <1.0.0,>=0.29.0
Requires-Dist: greenlet <4.0.0,>=3.0.3
